source_getlago/__init__.py
source_getlago/manifest.yaml
source_getlago/run.py
source_getlago/schemas/add_ons.json
source_getlago/schemas/billable_metrics.json
source_getlago/schemas/coupons.json
source_getlago/schemas/customer_usage.json
source_getlago/schemas/customers.json
source_getlago/schemas/fees.json
source_getlago/schemas/invoices.json
source_getlago/schemas/plans.json
source_getlago/schemas/subscriptions.json
source_getlago/schemas/wallets.json
source_getlago/source.py
source_getlago/spec.yaml
airbyte_source_getlago-0.4.11.dist-info/METADATA
airbyte_source_getlago-0.4.11.dist-info/WHEEL
airbyte_source_getlago-0.4.11.dist-info/entry_points.txt
airbyte_source_getlago-0.4.11.dist-info/RECORD
